LICENSE
README.md
setup.py
eiopt/__init__.py
eiopt/common.py
eiopt/constraint.py
eiopt/core.py
eiopt/model.py
eiopt/objective.py
eiopt/utils.py
eiopt.egg-info/PKG-INFO
eiopt.egg-info/SOURCES.txt
eiopt.egg-info/dependency_links.txt
eiopt.egg-info/requires.txt
eiopt.egg-info/top_level.txt
eiopt/algorithms/__init__.py
eiopt/algorithms/algorithm.py
eiopt/algorithms/ga.py
eiopt/variables/__init__.py
eiopt/variables/continuous.py
eiopt/variables/var_base.py
tests/test_GA.py
tests/test_common.py
tests/test_constraint.py
tests/test_eiopt.py
tests/test_model.py
tests/test_objective.py
tests/test_pyomo_case.py
tests/test_var.py