Metadata-Version: 2.1
Name: eiopt
Version: 0.0.4
Summary: description for Sample package
Home-page: http://www.eiopt.com/
Author: zmdsn
Author-email: zmdsn@126.com
License: 
License-File: LICENSE
